Metadata-Version: 2.1
Name: Flare-Helper
Version: 1.0.0
Summary: A python module used to make the authentication request more clean
Home-page: https://github.com/t-a-g-o/flare
Author: tago
License: MIT
License-File: LICENSE
